{"assets/fonts/sfmono.otf":["assets/fonts/sfmono.otf"],"assets/images/apps/1.jpg":["assets/images/apps/1.jpg"],"assets/images/apps/99.png":["assets/images/apps/99.png"],"assets/images/apps/ame.png":["assets/images/apps/ame.png"],"assets/images/apps/background1.json":["assets/images/apps/background1.json"],"assets/images/apps/background2.json":["assets/images/apps/background2.json"],"assets/images/apps/background3.json":["assets/images/apps/background3.json"],"assets/images/apps/background4.json":["assets/images/apps/background4.json"],"assets/images/apps/background5.json":["assets/images/apps/background5.json"],"assets/images/apps/c6.png":["assets/images/apps/c6.png"],"assets/images/apps/caixa.png":["assets/images/apps/caixa.png"],"assets/images/apps/facebook.png":["assets/images/apps/facebook.png"],"assets/images/apps/flutter.png":["assets/images/apps/flutter.png"],"assets/images/apps/gif.gif":["assets/images/apps/gif.gif"],"assets/images/apps/github.png":["assets/images/apps/github.png"],"assets/images/apps/instagram.png":["assets/images/apps/instagram.png"],"assets/images/apps/itau.png":["assets/images/apps/itau.png"],"assets/images/apps/linkedin.png":["assets/images/apps/linkedin.png"],"assets/images/apps/logo.png":["assets/images/apps/logo.png"],"assets/images/apps/mercadopago.png":["assets/images/apps/mercadopago.png"],"assets/images/apps/picpay.png":["assets/images/apps/picpay.png"],"assets/images/apps/pix.png":["assets/images/apps/pix.png"],"assets/images/apps/whatsapp.png":["assets/images/apps/whatsapp.png"],"assets/images/arrow_dark.json":["assets/images/arrow_dark.json"],"assets/images/arrow_light.json":["assets/images/arrow_light.json"],"assets/images/cell.png":["assets/images/cell.png"],"assets/images/cell.psd":["assets/images/cell.psd"],"assets/images/flutter.png":["assets/images/flutter.png"],"assets/images/hi_dark.json":["assets/images/hi_dark.json"],"assets/images/hi_light.json":["assets/images/hi_light.json"],"assets/images/profile.jpg":["assets/images/profile.jpg"],"assets/images/project1.png":["assets/images/project1.png"],"assets/images/project2.png":["assets/images/project2.png"],"assets/images/project3.png":["assets/images/project3.png"],"assets/images/project4.png":["assets/images/project4.png"],"assets/images/projectMobi1.png":["assets/images/projectMobi1.png"],"assets/images/projectMobi2.png":["assets/images/projectMobi2.png"],"assets/images/projectMobi3.png":["assets/images/projectMobi3.png"],"assets/images/projectMobi4.png":["assets/images/projectMobi4.png"],"assets/svg/github.svg":["assets/svg/github.svg"],"assets/svg/instagram.svg":["assets/svg/instagram.svg"],"assets/svg/linkedIn.svg":["assets/svg/linkedIn.svg"],"assets/svg/whatsapp.svg":["assets/svg/whatsapp.svg"],"packages/flutter_neumorphic_null_safety/fonts/NeumorphicIcons.ttf":["packages/flutter_neumorphic_null_safety/fonts/NeumorphicIcons.ttf"]}